{
	"messaging_product": "whatsapp",
	"recipient_type": "individual",
	"to": "",
	"type": "interactive",
	"interactive": {
		"type": "button",
		"body": {
			"text": "Clínica de olhos IMAV. Olá, espero que esteja bem. Não estamos disponíveis no momento. Nosso Horário de atendimento é de segunda à sexta-feira das 8h às 17h e aos sábados das 8h às 12h. Temos um menu abaixo caso necessite de alguma informação. Obrigado"
		},
		"action": {
			"buttons": [
				{
					"type": "reply",
					"reply": {
						"id": "button-telefone",
						"title": "TELEFONE DA IMAV"
					}
				},
				{
					"type": "reply",
					"reply": {
						"id": "button-whatsapp",
						"title": "WHATSAPP DA IMAV"
					}
				},
				{
					"type": "reply",
					"reply": {
						"id": "button-localizacao",
						"title": "LOCALIZAÇÃO/ENDEREÇO"
					}
				}
			]
		}
	}
}